image_builder_deployer/__init__.py
image_builder_deployer/__main__.py
image_builder_deployer/config_generator.py
image_builder_deployer/deploy_script.py
image_builder_deployer/gitlab_test.py
image_builder_deployer-0.6.7.dist-info/LICENSE.txt
image_builder_deployer-0.6.7.dist-info/METADATA
image_builder_deployer-0.6.7.dist-info/WHEEL
image_builder_deployer-0.6.7.dist-info/top_level.txt
image_builder_deployer-0.6.7.dist-info/RECORD
