Metadata-Version: 2.1
Name: image-builder-deployer
Version: 0.6.7
Summary: Deploys imageBuilder to GitHub
Home-page: https://github.com/pypa/sampleproject
Author: Vladimir Garanin
Author-email: vladimir.garanin@stfc.ac.uk
License: UNKNOWN
Project-URL: Bug Tracker, https://github.com/pypa/sampleproject/issues
Platform: UNKNOWN
Classifier: Programming Language :: Python :: 3
Classifier: License :: OSI Approved :: MIT License
Classifier: Operating System :: OS Independent
Requires-Python: >=3.6
License-File: LICENSE.txt
Requires-Dist: pynacl
Requires-Dist: requests
